<?xml version="1.0" encoding="utf-8"?>
<odoo>

    <data>
<!-- Tree view for base.rate -->
<record id="barcode_models_enhanced_view_tree" model="ir.ui.view">
    <field name="name">barcode.models.enhanced.view.tree</field>
        <field name="model">barcode.models.enhanced</field>
        <field name="arch" type="xml">
            <tree>
                <field name="name"/>
            </tree>
        </field>
    </record>

    <!-- Form view for base.rate -->
<record id="barcode_models_enhanced_view_form" model="ir.ui.view">
    <field name="name">barcode.models.enhanced.view.form</field>
        <field name="model">barcode.models.enhanced</field>
        <field name="arch" type="xml">
            <form string="Barcode Models Enhanced">
                <sheet>
                    <div class="oe_title">
                        <label for="name"/>
                        <h1>
                            <field name="name" placeholder="Name..."/>
                        </h1>
                    </div>
                </sheet>
            </form>
        </field>
    </record>

    <!-- Search view for base.rate -->
<record id="barcode_models_enhanced_view_search" model="ir.ui.view">
    <field name="name">barcode.models.enhanced.view.search</field>
        <field name="model">barcode.models.enhanced</field>
        <field name="arch" type="xml">
            <search>
                <group expand="1" string="Group By">
                    <filter string="Name" name="name" domain="[]" context="{'group_by':'name'}"/>
                </group>
            </search>
        </field>
    </record>

    <!-- Tree view for Action -->
    <record id="action_barcode_models_enhanced" model="ir.actions.act_window">
        <field name="name">Barcode Models Enhanced</field>
        <field name="type">ir.actions.act_window</field>
        <field name="res_model">barcode.models.enhanced</field>
        <field name="view_mode">tree,form</field>
        <field name="domain">[]</field>
        <field name="context">{}</field>
        <field name="help" type="html">
            <p class="oe_view_nocontent_create">
                There is no examples click here to add new Barcode Models Enhanced.
            </p>
        </field>
    </record>
</data>

</odoo>
