<?xml version="1.0" encoding="utf-8"?>
<odoo>
    <!-- Minimal action - let Odoo auto-generate views for portal.request -->
    <record id="action_portal_request" model="ir.actions.act_window">
        <field name="name">Portal Requests</field>
        <field name="res_model">portal.request</field>
        <field name="view_mode">tree,form</field>
        <field name="help" type="html">
            <p class="o_view_nocontent_smiling_face">
                Create your first record
            </p>
            <p>
                Manage customer portal service requests efficiently.
            </p>
        </field>
    </record>
</odoo>
